dictionary/__init__.py
dictionary/dictionary.py
mohas_very_simple_dictionary-2.0.1.dist-info/METADATA
mohas_very_simple_dictionary-2.0.1.dist-info/WHEEL
mohas_very_simple_dictionary-2.0.1.dist-info/top_level.txt
mohas_very_simple_dictionary-2.0.1.dist-info/RECORD
