Metadata-Version: 2.1
Name: mohas-very-simple-dictionary
Version: 2.0.1
Summary: UNKNOWN
Author: Mohammed S. Yaseen
License: UNKNOWN
Platform: UNKNOWN
Requires-Python: >=3.8
Requires-Dist: requests (>=2.23.0)
